qwack/__init__.py
qwack/main.py
qwack/models.py
qwack/tileset_cache.zip
qwack/u4_data.py
qwack/u4_tiler.py
qwack/dat/BRITAIN.ULT
qwack/dat/CHARSET.VGA
qwack/dat/COVE.ULT
qwack/dat/DEN.ULT
qwack/dat/EMPATH.ULT
qwack/dat/JHELOM.ULT
qwack/dat/LCB_1.ULT
qwack/dat/LCB_2.ULT
qwack/dat/LYCAEUM.ULT
qwack/dat/MAGINCIA.ULT
qwack/dat/MINOC.ULT
qwack/dat/MOONGLOW.ULT
qwack/dat/PAWS.ULT
qwack/dat/SERPENT.ULT
qwack/dat/SHAPES.VGA
qwack/dat/SKARA.ULT
qwack/dat/TRINSIC.ULT
qwack/dat/U4VGA.pal
qwack/dat/VESPER.ULT
qwack/dat/WORLD.MAP
qwack/dat/YEW.ULT
qwack/dat/appleII.zip
qwack/dat/jsteele-charset.ega
qwack/dat/jsteele-shapes.ega
qwack/dat/sf1.zip
qwack/dat/sf2.zip
qwack/dat/sf3.zip
qwack/dat/sf4.zip
qwack/dat/world.yaml
qwack-0.0.12.dist-info/METADATA
qwack-0.0.12.dist-info/WHEEL
qwack-0.0.12.dist-info/entry_points.txt
qwack-0.0.12.dist-info/top_level.txt
qwack-0.0.12.dist-info/zip-safe
qwack-0.0.12.dist-info/RECORD
