Metadata-Version: 2.4
Name: qwack
Version: 0.0.12
Summary: a rogue-like game of mysterious origins!
Home-page: https://github.com/jquast/qwack
Author: Jeff Quast
Author-email: contact@jeffquast.com
License: MIT
Requires-Dist: pyyaml
Requires-Dist: blessed
Dynamic: author
Dynamic: author-email
Dynamic: description
Dynamic: home-page
Dynamic: license
Dynamic: requires-dist
Dynamic: summary
